scene_graph_predictor_pc/__init__.py
scene_graph_predictor_pc/app.py
scene_graph_predictor_pc/inference.py
scene_graph_predictor_pc/config/vlsat.json
scene_graph_predictor_pc/data/classes.txt
scene_graph_predictor_pc/data/relationships.txt
scene_graph_predictor_pc/src/__init__.py
scene_graph_predictor_pc/src/model/__init__.py
scene_graph_predictor_pc/src/model/model.py
scene_graph_predictor_pc/src/model/model_utils/__init__.py
scene_graph_predictor_pc/src/model/model_utils/model_base.py
scene_graph_predictor_pc/src/model/model_utils/network_GNN.py
scene_graph_predictor_pc/src/model/model_utils/network_PointNet.py
scene_graph_predictor_pc/src/model/model_utils/network_util.py
scene_graph_predictor_pc/src/model/model_utils/networks_base.py
scene_graph_predictor_pc/src/model/vlsat/__init__.py
scene_graph_predictor_pc/src/model/vlsat/model.py
scene_graph_predictor_pc/src/utils/__init__.py
scene_graph_predictor_pc/src/utils/config.py
scene_graph_predictor_pc/src/utils/define.py
scene_graph_predictor_pc/src/utils/eval_utils.py
scene_graph_predictor_pc/src/utils/op_utils.py
scene_graph_predictor_pc/src/utils/optimizer.py
scene_graph_predictor_pc/src/utils/util.py
scene_graph_predictor_pc/src/utils/util_data.py
scene_graph_predictor_pc/src/utils/util_ply.py
scene_graph_predictor_pc-0.1.1.dist-info/METADATA
scene_graph_predictor_pc-0.1.1.dist-info/WHEEL
scene_graph_predictor_pc-0.1.1.dist-info/top_level.txt
scene_graph_predictor_pc-0.1.1.dist-info/RECORD
