Metadata-Version: 2.1
Name: scene-graph-predictor-pc
Version: 0.1.1
Summary: 3D Scene Graph Models
Home-page: https://github.com/wtt0213/scene-graph-predictor-pc
Download-URL: https://github.com/wtt0213/scene-graph-predictor-pc/tags
Author: Ziqin Wang
Author-email: wzqbuaa@qq.com
Requires-Python: >=3.8
Requires-Dist: trimesh (==3.12.7)
Requires-Dist: open3d (==0.16.0)
Requires-Dist: aiofiles
Requires-Dist: fastapi
Requires-Dist: uvicorn[standard]
Requires-Dist: python-multipart
